MANIFEST.in
README.md
requirements.txt
setup.cfg
setup.py
aufbau/__init__.py
aufbau.egg-info/PKG-INFO
aufbau.egg-info/SOURCES.txt
aufbau.egg-info/dependency_links.txt
aufbau.egg-info/entry_points.txt
aufbau.egg-info/not-zip-safe
aufbau.egg-info/top_level.txt