Metadata-Version: 1.1
Name: aufbau
Version: 0.1.0
Summary: A toolkit for writing build scripts for .NET projects in Python.
Home-page: https://github.com/jammycakes/aufbau
Author: James McKay
Author-email: code@jamesmckay.net
License: MIT
Download-URL: https://github.com/jammycakes/aufbau/archive/0.1.0.tar.gz
Keywords: dotnet,build
Platform: UNKNOWN
Classifier: Development Status :: 3 - Alpha
Classifier: License :: OSI Approved :: MIT License
Classifier: Programming Language :: Python :: 3.6
